{"lastUsed":1679832004133,"path":"G:\/Web_Technologies_in_JAVA","projectCount":1,"recentFiles":[{"path":"\/Student_Information\/src\/main\/java\/Connection","parentWorkspace":"G:\/Web_Technologies_in_JAVA","name":"DBConnection.java","lastModified":1679740337914,"locationURI":"file:\/G:\/Web_Technologies_in_JAVA\/Student_Information\/src\/main\/java\/Connection\/DBConnection.java"},{"path":"\/Student_Information\/src\/main\/webapp","parentWorkspace":"G:\/Web_Technologies_in_JAVA","name":"Student-Home.jsp","lastModified":1679831701182,"locationURI":"file:\/G:\/Web_Technologies_in_JAVA\/Student_Information\/src\/main\/webapp\/Student-Home.jsp"},{"path":"\/Student_Information\/src\/main\/webapp","parentWorkspace":"G:\/Web_Technologies_in_JAVA","name":"Index.jsp","lastModified":1679809086261,"locationURI":"file:\/G:\/Web_Technologies_in_JAVA\/Student_Information\/src\/main\/webapp\/Index.jsp"},{"path":"\/Student_Information\/src\/main\/webapp","parentWorkspace":"G:\/Web_Technologies_in_JAVA","name":"Student-Login.jsp","lastModified":1679807465424,"locationURI":"file:\/G:\/Web_Technologies_in_JAVA\/Student_Information\/src\/main\/webapp\/Student-Login.jsp"},{"path":"\/Student_Information\/src\/main\/webapp","parentWorkspace":"G:\/Web_Technologies_in_JAVA","name":"Student-Logout.jsp","lastModified":1679740613217,"locationURI":"file:\/G:\/Web_Technologies_in_JAVA\/Student_Information\/src\/main\/webapp\/Student-Logout.jsp"},{"path":"\/Student_Information\/src\/main\/java\/Controller","parentWorkspace":"G:\/Web_Technologies_in_JAVA","name":"StudentController.java","lastModified":1679757921943,"locationURI":"file:\/G:\/Web_Technologies_in_JAVA\/Student_Information\/src\/main\/java\/Controller\/StudentController.java"},{"path":"\/Student_Information\/src\/main\/java\/Model","parentWorkspace":"G:\/Web_Technologies_in_JAVA","name":"Student.java","lastModified":1679831595436,"locationURI":"file:\/G:\/Web_Technologies_in_JAVA\/Student_Information\/src\/main\/java\/Model\/Student.java"},{"path":"\/Student_Information\/src\/main\/java\/Dao","parentWorkspace":"G:\/Web_Technologies_in_JAVA","name":"StudentDao.java","lastModified":1679830116174,"locationURI":"file:\/G:\/Web_Technologies_in_JAVA\/Student_Information\/src\/main\/java\/Dao\/StudentDao.java"},{"path":"\/Student_Information\/src\/main\/webapp","parentWorkspace":"G:\/Web_Technologies_in_JAVA","name":"Student-Update.jsp","lastModified":1679832015536,"locationURI":"file:\/G:\/Web_Technologies_in_JAVA\/Student_Information\/src\/main\/webapp\/Student-Update.jsp"},{"path":"\/Student_Information\/src\/main\/webapp","parentWorkspace":"G:\/Web_Technologies_in_JAVA","name":"Student-Registration.jsp","lastModified":1679807172627,"locationURI":"file:\/G:\/Web_Technologies_in_JAVA\/Student_Information\/src\/main\/webapp\/Student-Registration.jsp"}]}